{
    "display_title": "Portfolio",
	"short_description" : "What you are currently looking at is my portfolio page. I developed this platform using ReactJS through Gatsby with TypeScript. When I was first looking into the best platform choice for this project I had two things in mind: SEO & Reactivity, and that's exactly what Gatsby provides. This was a short but sweet project that I really enjoyed working on.",
    "raw_md" : "# Hello World",
    "repo_url" : "https://github.com/liamdebellada/portfolio/",
	"display_image" : "/collections/portfolio.webp",
	"display_slide" : "/slides/portfolio.webp"
}
